Metadata-Version: 1.2
Name: nekoplot
Version: 0.1.1
Summary: Small, WIP graphing package.
Home-page: http://neko-bot.net/nekoplot
Author: LazyNeko
Author-email: lazynekoo@gmail.com
License: UNKNOWN
Platform: UNKNOWN
Requires-Python: >=3.6
